Metadata-Version: 1.0
Name: Coordiantes-simplify
Version: 0.2
Summary: You may add subtract multiply divide
Home-page: UNKNOWN
Author: UNKNOWN
Author-email: UNKNOWN
License: UNKNOWN
Platform: UNKNOWN
